templates/__init__.py
web/__init__.py
web/asgi.py
web/settings.py
web/urls.py
web/views.py
web/wsgi.py
ai_agent_app-0.1.0.dist-info/METADATA
ai_agent_app-0.1.0.dist-info/WHEEL
ai_agent_app-0.1.0.dist-info/top_level.txt
ai_agent_app-0.1.0.dist-info/RECORD
