Metadata-Version: 2.1
Name: ai-agent-app
Version: 0.1.0
Summary: ai agent CIT
Home-page: https://github.com/sebastian_coros/ai_agent_app
Author: Sebastian Coros
Author-email: sebastian.coros@dell.com
License: UNKNOWN
Platform: UNKNOWN
Classifier: Programming Language :: Python :: 3
Classifier: License :: OSI Approved :: MIT License
Classifier: Operating System :: OS Independent
Requires-Python: >=3.6
